wild_computing_machine/__init__.py
wild_computing_machine/common.py
wild_computing_machine/constants.py
wild_computing_machine/effector.py
wild_computing_machine/shaper.py
wild_computing_machine/wild_comp.py
wild_computing_machine-0.0.1.dist-info/METADATA
wild_computing_machine-0.0.1.dist-info/RECORD
wild_computing_machine-0.0.1.dist-info/WHEEL
wild_computing_machine-0.0.1.dist-info/top_level.txt
