Metadata-Version: 2.1
Name: wild-computing-machine
Version: 0.0.1
Summary: Chaotic Stupid D&D spell generator
Home-page: https://github.com/c-x-berger/wild-computing-machine
Author: Caleb Xavier Berger
Author-email: caleb.x.berger@gmail.com
License: UNKNOWN
Platform: UNKNOWN
Classifier: Programming Language :: Python :: 3
Classifier: License :: OSI Approved :: MIT License
Classifier: Operating System :: OS Independent
